CHANGELOG
setup.py
setup.py.bak
LyricSearch.egg-info/PKG-INFO
LyricSearch.egg-info/SOURCES.txt
LyricSearch.egg-info/dependency_links.txt
LyricSearch.egg-info/entry_points.txt
LyricSearch.egg-info/requires.txt
LyricSearch.egg-info/top_level.txt
dist/LyricSearch-0.1-py2.4.egg
dist/LyricSearch-0.1.2-py2.4.egg
dist/LyricSearch-0.1.2.tar.gz
dist/LyricSearch-0.1.9-py2.4.egg
dist/LyricSearch-0.1.9.zip
dist/LyricSearch-0.2.0-py2.4.egg
lyricsearch/__init__.py
lyricsearch/__init__.pyc
lyricsearch/lyricastraweb.py
lyricsearch/lyricastraweb.py.bak
lyricsearch/lyricastraweb.pyc
lyricsearch/lyricterra.py
lyricsearch/lyricterra.py.bak
lyricsearch/lyricterra.pyc
lyricsearch/lyse.py
lyricsearch/lyse.py.bak
lyricsearch/lyse.pyc
