Metadata-Version: 1.0
Name: LyricSearch
Version: 0.2.1
Summary: script for lyrics search in web
Home-page: UNKNOWN
Author: Claudio Torcato
Author-email: clauditorcato@gmail.com
License: UNKNOWN
Platform: UNKNOWN
Classifier: Development Status :: 4 - Beta
Classifier: Environment :: Console
Classifier: Intended Audience :: End Users/Desktop
Classifier: Operating System :: MacOS :: MacOS X
Classifier: Operating System :: Microsoft :: Windows
Classifier: Operating System :: POSIX
Classifier: Programming Language :: Python
Classifier: Natural Language :: Portuguese (Brazilian)
